{
  "name": "wiki_page_deleted",
  "definition": "The event is emitted anytime a wiki page is deleted by an end user or API request.",
  "trigger": "Triggered when a wiki page is deleted.",
  "schema": {
    "title": "The title of the deleted wiki page. NOTE: This field will be truncated to only include the first 8192 characters.",
    "wiki_page_id": "The Canvas id of the deleted wiki page."
  },
  "examples": [
    {
      "payload": {
        "metadata": {
          "client_ip": "93.184.216.34",
          "context_account_id": "21070000000000079",
          "context_id": "21070000000000565",
          "context_role": "TeacherEnrollment",
          "context_sis_source_id": "2017.100.101.101-1",
          "context_type": "Course",
          "event_name": "wiki_page_deleted",
          "event_time": "2019-11-01T19:11:13.729Z",
          "hostname": "oxana.instructure.com",
          "http_method": "DELETE",
          "producer": "canvas",
          "referrer": "https://oxana.instructure.com/courses/1013182/pages/ccs-online-logo-instructions?module_item_id=9653761",
          "request_id": "1dd9dc6f-2fb0-4c19-a6c5-7ee1bf3ed295",
          "root_account_id": "21070000000000001",
          "root_account_lti_guid": "VicYj3cu5BIFpoZhDVU4DZumnlBrWi1grgJEzADs.oxana.instructure.com",
          "root_account_uuid": "VicYj3cu5BIFpoZhDVU4DZumnlBrWi1grgJEzADs",
          "session_id": "ef686f8ed684abf78cbfa1f6a58112b5",
          "time_zone": "America/Los_Angeles",
          "url": "https://oxana.instructure.com/api/v1/courses/1499839/pages/ccs-online-logo-instructions",
          "user_account_id": "21070000000000001",
          "user_agent": "Mozilla/5.0 (Macintosh; Intel Mac OS X 10_14_3) AppleWebKit/537.36 (KHTML, like Gecko) Chrome/73.0.3683.103 Safari/537.36",
          "user_id": "21070000000000001",
          "user_login": "oxana@example.com",
          "user_sis_id": "456-T45"
        },
        "body": {
          "title": "Page 1 Updated",
          "wiki_page_id": "21070000000000009"
        }
      }
    }
  ]
}